huggingpics/__init__.py
huggingpics/classifier.py
huggingpics/data.py
huggingpics-0.0.1.dist-info/METADATA
huggingpics-0.0.1.dist-info/WHEEL
huggingpics-0.0.1.dist-info/top_level.txt
huggingpics-0.0.1.dist-info/RECORD
