Metadata-Version: 2.1
Name: huggingpics
Version: 0.0.1
Summary: 🤗🖼️ HuggingPics: Fine-tune Vision Transformers for anything using images found on the web.
Home-page: https://github.com/nateraw/huggingpics
Author: Nathan Raw
Author-email: naterawdata@gmail.com
License: MIT
Platform: UNKNOWN
Requires-Dist: torch
Requires-Dist: torchvision
Requires-Dist: pytorch-lightning
Requires-Dist: transformers
